folderclean/__init__.py
folderclean/command_line.py
folderclean-1.2.dist-info/LICENSE
folderclean-1.2.dist-info/METADATA
folderclean-1.2.dist-info/WHEEL
folderclean-1.2.dist-info/entry_points.txt
folderclean-1.2.dist-info/top_level.txt
folderclean-1.2.dist-info/RECORD
