Metadata-Version: 2.1
Name: folderclean
Version: 1.2
Summary: Clean your folders in a single line of code! FolderCleans lets you for example clean your folders and organize them by file types.
Home-page: https://github.com/Animenosekai/folder_cleaner
Author: Anime no Sekai
Author-email: niichannomail@gmail.com
License: MIT
Download-URL: https://github.com/Animenosekai/folder_cleaner/archive/v1.2.tar.gz
Keywords: clean,folder,directory,cleaning,folderclean,animenosekai,sort,filecenter,lifeeasy
Platform: UNKNOWN
Classifier: Development Status :: 4 - Beta
Classifier: License :: OSI Approved :: MIT License
Classifier: Programming Language :: Python :: 3
Classifier: Programming Language :: Python :: 3.4
Classifier: Programming Language :: Python :: 3.5
Classifier: Programming Language :: Python :: 3.6
Classifier: Programming Language :: Python :: 3.7
Classifier: Programming Language :: Python :: 3.8
Requires-Dist: filecenter
Requires-Dist: lifeeasy
